bbp/__init__.py
bbp/wrapper.py
bbp-0.1.dist-info/LICENSE.txt
bbp-0.1.dist-info/METADATA
bbp-0.1.dist-info/WHEEL
bbp-0.1.dist-info/top_level.txt
bbp-0.1.dist-info/RECORD
